{
    "schema_version": 1,
    "overrides": [
        {
            "id": "create",
            "breaks": [
                {
                    "replace": {
                        "id": "sound_physics_remastered",
                        "versions": "*"
                    },
                    "with": {
                        "id": "sound_physics_remastered",
                        "versions": "<1.4.0"
                    }
                }
            ]
        },
        {
            "id": "nvidium",
            "depends": [
                {
                    "replace": {
                        "id": "sodium",
                        "versions": ["=0.5.7", "=0.5.8"]
                    },
                    "with": {
                        "id": "sodium",
                        "versions": ">=0.5.7"
                    }
                }
            ]
        }
    ]
}
